{
    "web": {
        "https://kbopping.com/blackpink/": {
            "title": "Blackpink",
            "content": ""
        },
        "https://kbopping.com/the-shortest-record-in-instagram-history-bts-v-surpasses-40-million-followers/": {
            "title": "\u201cThe shortest record in Instagram history\u201d BTS V surpasses 40 million followers",
            "content": ""
        },
        "https://kbopping.com/bigbangs-daesung-wins-1st-place-on-m-countdown-its-an-honor-to-be-recorded-together-in-your-past-and-present/": {
            "title": "Bigbang\u2019s Daesung wins 1st place on \u2018M Countdown\u2019\u2026\u201dIt\u2019s an honor to be recorded together in your past and present\u201d",
            "content": ""
        },
        "https://kbopping.com/bts-14th-week-of-billboards-hot-100-top-10/": {
            "title": "BTS, 14th week of Billboard\u2019s \u2018Hot 100\u2019 Top 10",
            "content": ""
        },
        "https://kbopping.com/bts/": {
            "title": "BTS",
            "content": ""
        },
        "https://kbopping.com/seventeen-4th-regular-album-release-on-may-27th/": {
            "title": "SEVENTEEN, 4th regular album release on May 27th",
            "content": ""
        },
        "https://kbopping.com/35th-golden-blackpink%c2%b7itzy%c2%b7twice%c2%b7red-velvet-ireneseulgi%c2%b7mamamoo%c2%b7iu/": {
            "title": "[35th Golden] BLACKPINK\u00b7ITZY\u00b7TWICE\u00b7Red Velvet-Irene&Seulgi\u00b7MAMAMOO\u00b7IU",
            "content": ""
        },
        "https://kbopping.com/bts-my-universe-tops-us-billboard-chart-for-29th-week/": {
            "title": "BTS, \u2018My Universe\u2019 tops US Billboard chart for 29th week",
            "content": ""
        },
        "https://kbopping.com/high-school-rapper-4-seung-hoon-lee-is-the-final-winner/": {
            "title": "\u2018High School Rapper 4\u2019 Seung-Hoon Lee is the final winner",
            "content": ""
        },
        "https://kbopping.com/departure-on-the-20th-for-the-coachella-performance-aespa-writes-a-new-history/": {
            "title": "Departure on the 20th for the \u2018Coachella\u2019 performance, Aespa writes a new history",
            "content": ""
        },
        "https://kbopping.com/k-pop-weekly-chart-billboard-2022-04-17/": {
            "title": "K-POP WEEKLY CHART \u2013 BILLBOARDK",
            "content": ""
        },
        "https://kbopping.com/after-school-nana-a-dizzying-pose-%e2%86%92-kahi-is-also-surprised-oh-huh/": {
            "title": "After School Nana, a dizzying pose \u2192 Kahi is also surprised, \u201cOh huh",
            "content": ""
        },
        "https://kbopping.com/ive-entered-the-top-10-on-billboards-global-chart/": {
            "title": "IVE entered the top 10 on Billboard\u2019s global chart",
            "content": ""
        },
        "https://kbopping.com/2020-tma-super-juniors-new-song-stage-first-released-%e2%86%92-hee-cheol-kim-joined/": {
            "title": "\u20182020 TMA\u2019 Super Junior\u2019s new song stage first released \u2192 Hee-cheol Kim joined",
            "content": ""
        },
        "https://kbopping.com/purple-kiss-pretty-psycho-performance-video-released/": {
            "title": "Purple Kiss, \u2018Pretty Psycho\u2019 performance video released",
            "content": ""
        },
        "https://kbopping.com/kpop-social-media-trends-on-02-16-2022-treasures-jikjin-and-apinks-dilemma/": {
            "title": "Kpop Social Media Trends on 02-16-2022: TREASURE\u2019s \u2018JIKJIN\u2019 and Apink\u2019s \u2018Dilemma\u2019",
            "content": ""
        },
        "https://kbopping.com/k-pop-weekly-chart-billboard-2022-04-10/": {
            "title": "K-POP WEEKLY CHART \u2013 BILLBOARDK",
            "content": ""
        },
        "https://kbopping.com/pre-orders-for-tomorrow-x-togethers-4th-mini-album-exceeded-816000/": {
            "title": "Pre-orders for TOMORROW X TOGETHER\u2019s 4th mini-album exceeded 816,000",
            "content": ""
        },
        "https://kbopping.com/psy-reveals-additional-information-on-3-songs-from-the-9th-regular-album-giriboy-crush-sung-sikyung-and-heize-support/": {
            "title": "PSY reveals additional information on 3 songs from the 9th regular album.. Giriboy, Crush, Sung Sikyung, and Heize Support",
            "content": ""
        },
        "https://kbopping.com/mcnd-unveiled-juice-on-the-european-tour-stage-swag-exploded/": {
            "title": "MCND unveiled \u2018JUICE\u2019 on the European Tour stage\u2026 SWAG exploded",
            "content": ""
        },
        "https://kbopping.com/dreamcatcher-is-promoting-apocalypse-save-us-in-the-first-week/": {
            "title": "DREAMCATCHER is promoting \u201cApocalypse : Save us\u201d in the first week",
            "content": ""
        },
        "https://kbopping.com/blackpink-lisas-new-pictorial-elle/": {
            "title": "Blackpink Lisa\u2019s new pictorial\u2026  Elle",
            "content": ""
        },
        "https://kbopping.com/k-pop-daily-chart-apple-music-2022-04-20/": {
            "title": "APPLE MUSIC 100 in KoreaA",
            "content": ""
        },
        "https://kbopping.com/monsta-x-the-ultimate-visual/": {
            "title": "MONSTA X, the ultimate visual",
            "content": ""
        },
        "https://kbopping.com/everglow-releases-pirate-remix-sound-source-with-dj-r3hab/": {
            "title": "Everglow releases \u2018Pirate\u2019 remix sound source with DJ R3HAB",
            "content": ""
        },
        "https://kbopping.com/purple-kiss-memem-performance-video/": {
            "title": "Purple Kiss \u2018memeM\u2019 performance video",
            "content": ""
        },
        "https://kbopping.com/k-pop-daily-chart-apple-music-2022-04-24/": {
            "title": "APPLE MUSIC 100 in KoreaA",
            "content": ""
        },
        "https://kbopping.com/bts-transforms-las-vegas-into-borahaegas/": {
            "title": "BTS transforms Las Vegas into \u2018Borahaegas\u2019",
            "content": ""
        },
        "https://kbopping.com/god-the-beat-step-back-mv-hits-100-million-views/": {
            "title": "God the Beat \u2018Step Back\u2019 MV hits 100 million views",
            "content": ""
        },
        "https://kbopping.com/loona-queendom-2-ambush/": {
            "title": "Loona, \u2018Queendom 2\u2019 ambush",
            "content": ""
        },
        "https://kbopping.com/treasure-darari-performance-video-with-challenge-movements/": {
            "title": "Treasure \u2018DARARI\u2019 performance video with challenge movements",
            "content": ""
        },
        "https://kbopping.com/my-gi-dle-miyeon-first-solo-album-scheduler-released/": {
            "title": "\u2018MY\u2019 (G)I-DLE Miyeon, first solo album scheduler released",
            "content": ""
        },
        "https://kbopping.com/queendom-2-wjsn-turns-crisis-into-opportunity-navillera-unrivaled-performance-praise/": {
            "title": "\u2018Queendom 2\u2019 WJSN turns crisis into opportunity\u2026 \u2018NAVILLERA\u2019 unrivaled performance praise",
            "content": ""
        },
        "https://kbopping.com/april-girl-group-brand-reputation-1st-gi-dle-2nd-blackpink-3rd-red-velvet-korea-corporate-reputation-research-institute/": {
            "title": "April Girl group brand reputation\u2026 1st (G)I-DLE, 2nd Blackpink, 3rd Red Velvet (Korea Corporate Reputation Research Institute)",
            "content": ""
        },
        "https://kbopping.com/eun-bi-kwon-glitch-mv-surpasses-10-million-views-global-popularity/": {
            "title": "Eun Bi Kwon, \u2018Glitch\u2019 MV surpasses 10 million views\u2026 Global popularity",
            "content": ""
        },
        "https://kbopping.com/ateez-japanese-2nd-mini-album-release-on-may-25th/": {
            "title": "ATEEZ, Japanese 2nd Mini Album Release on May 25th",
            "content": ""
        },
        "https://kbopping.com/boa-releases-the-4th-song-do-the-motion-of-self-cover-project-in-japan-on-the-11th/": {
            "title": "BoA releases the 4th song \u2018Do the Motion\u2019 of \u2018Self Cover Project\u2019 in Japan on the 11th",
            "content": ""
        },
        "https://kbopping.com/k-pop-daily-chart-apple-music-2022-04-21/": {
            "title": "APPLE MUSIC 100 in KoreaA",
            "content": ""
        },
        "https://kbopping.com/twenty-five-twenty-one-wjsn-bona-ranked-2nd-in-april-girl-group-personal-brand-reputation-will-it-even-surpass-no-1-jennie/": {
            "title": "\u2018Twenty-Five Twenty One\u2019 WJSN Bona ranked 2nd in April girl group personal brand reputation\u2026 Will it even surpass No. 1 Jennie?",
            "content": ""
        },
        "https://kbopping.com/k-pop-daily-chart-apple-music-2022-04-17/": {
            "title": "APPLE MUSIC 100 in KoreaA",
            "content": ""
        },
        "https://kbopping.com/heeseung-the-fourth-runner-of-enhypen-en-log-buy-a-suit-%e2%86%92-visit-a-dog-cafe-sharing-small-daily-life/": {
            "title": "Heeseung, the fourth runner of Enhypen, \u2018EN-LoG\u2019.. \u2018Buy a suit \u2192 visit a dog cafe\u2019 Sharing small daily life",
            "content": ""
        },
        "https://kbopping.com/bts-jungkook-instagrams-2-days-in-a-row-daily-follower-increase-1st-place-social-king/": {
            "title": "BTS Jungkook, Instagram\u2019s \u20182 days in a row\u2019 daily follower increase, 1st place. \u2018Social King\u2019!",
            "content": ""
        },
        "https://kbopping.com/shinee-onew-adds-diversity-to-its-unique-tone/": {
            "title": "SHINee Onew adds \u2018diversity\u2019 to its unique tone",
            "content": ""
        },
        "https://kbopping.com/bts-came-back-on-the-19th-start-preparing-for-a-new-album/": {
            "title": "BTS came back on the 19th\u2026 Start preparing for a new album",
            "content": ""
        },
        "https://kbopping.com/tnx-releases-teaser-video-ahead-of-its-debut/": {
            "title": "TNX releases teaser video ahead of its debut",
            "content": ""
        },
        "https://kbopping.com/k-pop-daily-chart-apple-music-2022-04-10/": {
            "title": "APPLE MUSIC 100 in KoreaA",
            "content": ""
        },
        "https://kbopping.com/k-pop-daily-chart-apple-music-2022-04-11/": {
            "title": "APPLE MUSIC 100 in KoreaA",
            "content": ""
        },
        "https://kbopping.com/comeback-on-may-3-ikon-the-title-song-is-but-you/": {
            "title": "\u201cComeback on May 3\u201d iKON, the title song is \u2018BUT YOU\u2019",
            "content": ""
        },
        "https://kbopping.com/bts-v-we-failed-to-win-the-grammy-it-was-neat-admit/": {
            "title": "BTS V \u201cWe failed to win the Grammy, it was neat\u2026 admit!\u201d",
            "content": ""
        },
        "https://kbopping.com/announcement-of-comeback-on-may-3-ikons-flashback/": {
            "title": "Announcement of comeback on May 3\u2026 iKON\u2019s \u2018FLASHBACK\u2019",
            "content": ""
        },
        "https://kbopping.com/inkigayo-bigbang-start-hunting-for-the-1st-place-trophy-shinee-onew-and-jessie-comeback/": {
            "title": "\u2018Inkigayo\u2019 Bigbang, start hunting for the 1st place trophy\u2026 Shinee Onew and Jessie comeback",
            "content": ""
        },
        "https://kbopping.com/exos-10th-anniversary-fan-event-has-been-completed-we-are-all-happy-to-celebrate-our-10th-anniversary-together/": {
            "title": "EXO\u2019s 10th anniversary fan event has been completed\u2026 \u201cWe are all happy to celebrate our 10th anniversary together\u201d",
            "content": ""
        },
        "https://kbopping.com/seventeens-visual-is-fantastic-darling-concept-photos-released/": {
            "title": "SEVENTEEN\u2019s visual is fantastic\u2026 \u2018Darl+ing\u2019 concept photos released",
            "content": ""
        },
        "https://kbopping.com/ive-1st-place-on-the-show-love-dive/": {
            "title": "IVE, 1st place on \u2018The Show\u2019\u2026\u2019Love Dive\u2019",
            "content": ""
        },
        "https://kbopping.com/k-pop-daily-chart-apple-music-2022-04-22/": {
            "title": "APPLE MUSIC 100 in KoreaA",
            "content": ""
        },
        "https://kbopping.com/le-sserafim-sakura-the-gorgeous-goddess-of-spring/": {
            "title": "Le Sserafim Sakura, the gorgeous \u2018Goddess of Spring\u2019",
            "content": ""
        },
        "https://kbopping.com/hybes-first-girl-group-le-sserafim-unveils-a-six-member-group-with-bold-charm/": {
            "title": "\u2018HYBE\u2019s first girl group\u2019 Le Sserafim, unveils a six-member group with bold charm",
            "content": ""
        },
        "https://kbopping.com/k-pop-daily-chart-apple-music-2022-04-15/": {
            "title": "APPLE MUSIC 100 in KoreaA",
            "content": ""
        },
        "https://kbopping.com/k-pop-daily-chart-apple-music-2022-04-19/": {
            "title": "APPLE MUSIC 100 in KoreaA",
            "content": ""
        },
        "https://kbopping.com/bigbang-sweeps-the-charts-for-the-6th-day/": {
            "title": "Bigbang sweeps the charts for the 6th day",
            "content": ""
        },
        "https://kbopping.com/treasures-first-concert-full-of-joy-and-tears/": {
            "title": "TREASURE\u2019s first concert full of joy and tears",
            "content": ""
        },
        "https://kbopping.com/sunmi-exuding-an-aura-from-the-sidewalk-block/": {
            "title": "Sunmi exuding an aura from the sidewalk block",
            "content": ""
        },
        "https://kbopping.com/le-sserafim-releases-debut-trailer/": {
            "title": "Le Sserafim Releases Debut Trailer",
            "content": ""
        },
        "https://kbopping.com/seventeen-releases-their-first-english-single-darling/": {
            "title": "SEVENTEEN releases their first English single \u2018Darl+ing\u2019",
            "content": ""
        },
        "https://kbopping.com/super-rookie-kepler-debut-song-wa-da-da-mv-surpasses-100-million-views/": {
            "title": "\u2018Super Rookie\u2019 Kepler, debut song \u2018WA DA DA\u2019 MV surpasses 100 million views",
            "content": ""
        },
        "https://kbopping.com/k-pop-daily-chart-apple-music-2022-04-13/": {
            "title": "APPLE MUSIC 100 in KoreaA",
            "content": ""
        },
        "https://kbopping.com/psy-will-his-concert-resume/": {
            "title": "PSY, will his concert resume?",
            "content": ""
        },
        "https://kbopping.com/seventeen-its-spring/": {
            "title": "Seventeen, it\u2019s spring",
            "content": ""
        },
        "https://kbopping.com/gi-dles-miyeon-new-song-my-romantic-mood-concept-photo-released/": {
            "title": "(G)I-dle\u2019s Miyeon, new song \u2018MY\u2019 romantic mood concept photo released",
            "content": ""
        },
        "https://kbopping.com/winner-ikon-treasure-bigbangs-still-life-spring-summer-fall-winter-reaction/": {
            "title": "Winner, iKon, Treasure, Bigbang\u2019s \u2018Still Life (Spring, Summer, Fall, Winter)\u2019 Reaction?",
            "content": ""
        },
        "https://kbopping.com/nct-dream-glitch-mode-1st-in-united-world-chart/": {
            "title": "NCT Dream \u2018Glitch Mode\u2019 1st in United World Chart",
            "content": ""
        },
        "https://kbopping.com/ive-overtook-bigbang-to-take-the-top-spot-on-music-bank-i-love-you-dive/": {
            "title": "IVE overtook BIGBANG to take the top spot on Music Bank\u2026 \u201cI love you DIVE\u201d",
            "content": ""
        },
        "https://kbopping.com/2ne1-is-back-in-7-years-coachella/": {
            "title": "2NE1 is back in 7 years!  Coachella",
            "content": ""
        },
        "https://kbopping.com/epik-high-ends-long-north-american-tour-global-popularity-even-to-coachella-in-the-us/": {
            "title": "Epik High Ends Long North American Tour\u2026 Global popularity even to Coachella in the US",
            "content": ""
        },
        "https://kbopping.com/apple-tim-cook-looking-forward-to-seventeen-x-apple-collaboration-we-are-thrilled-to-have-you/": {
            "title": "Apple Tim Cook, looking forward to SEVENTEEN x Apple collaboration\u2026 \u201cWe are thrilled to have you!\u201d",
            "content": ""
        },
        "https://kbopping.com/ive-top-5-in-initial-sales-among-girl-groups-only-4-months-since-their-debut/": {
            "title": "IVE, top 5 in Initial Sales among girl groups\u2026 Only 4 months since their debut",
            "content": ""
        },
        "https://kbopping.com/nmixx-o-o-mv-60-million-views-moving-forward-towards-100-million-views/": {
            "title": "NMIXX \u2018O.O\u2019 MV 60 million views\u2026 Moving forward towards 100 million views",
            "content": ""
        },
        "https://kbopping.com/bigbang-loved-by-people-of-all-ages/": {
            "title": "BIGBANG, loved by people of all ages",
            "content": ""
        },
        "https://kbopping.com/ravi-to-hold-a-solo-concert-on-the-7th-and-8th-of-next-month/": {
            "title": "RAVI to hold a solo concert on the 7th and 8th of next month",
            "content": ""
        },
        "https://kbopping.com/btss-boy-with-luv-feat-halsey-surpassed-1-5-billion-views/": {
            "title": "BTS\u2019s \u201cBoy With Luv (Feat. Halsey)\u201d surpassed 1.5 billion views",
            "content": ""
        },
        "https://kbopping.com/k-pop-daily-chart-apple-music-2022-04-23/": {
            "title": "APPLE MUSIC 100 in KoreaA",
            "content": ""
        },
        "https://kbopping.com/kpop-social-media-trends-on-04-15-2022-ives-love-dive-and-just-bs-reload/": {
            "title": "Kpop Social Media Trends on 04-15-2022: IVE\u2019s \u2018LOVE DIVE\u2019 and JUST B\u2019s \u2018RE=LOAD\u201d",
            "content": ""
        },
        "https://kbopping.com/enhypen-ni-ki-reveals-small-daily-life-with-jay-and-jungwon-global-fan-communication/": {
            "title": "Enhypen Ni-ki reveals small daily life with Jay and Jungwon..Global fan communication",
            "content": ""
        },
        "https://kbopping.com/seventeen-mtv-fresh-out-live-in-the-us/": {
            "title": "SEVENTEEN, \u2018MTV Fresh Out Live\u2019 in the US",
            "content": ""
        },
        "https://kbopping.com/exos-10th-anniversary-of-debut-with-fans/": {
            "title": "EXO\u2019s 10th anniversary of debut \u2018with fans\u2019",
            "content": ""
        },
        "https://kbopping.com/le-sserafims-fearless-show-unveiled-a-strong-first-step/": {
            "title": "Le Sserafim\u2019s \u2018Fearless Show\u2019 unveiled, a strong first step",
            "content": ""
        },
        "https://kbopping.com/tomorrow-x-together-with-their-4th-mini-album-4th-generation-leader/": {
            "title": "Tomorrow X Together with their 4th mini album, \u20184th generation leader\u2019",
            "content": ""
        },
        "https://kbopping.com/ikon-to-make-a-full-comeback-after-1-year-coming-soon-poster-surprise-release/": {
            "title": "iKON to make a full comeback after 1 year\u2026 Coming Soon poster surprise release",
            "content": ""
        },
        "https://kbopping.com/monsta-x-releases-shape-of-love-on-the-26th/": {
            "title": "MONSTA X releases \u2018Shape of Love\u2019 on the 26th",
            "content": ""
        },
        "https://kbopping.com/bts-in-las-audition-applicants-dreaming-of-the-next-bts/": {
            "title": "[BTS in LAS] Audition applicants dreaming of the next BTS",
            "content": ""
        },
        "https://kbopping.com/k-pop-daily-chart-apple-music-2022-04-18/": {
            "title": "APPLE MUSIC 100 in KoreaA",
            "content": ""
        },
        "https://kbopping.com/ikon-to-hold-its-first-online-fan-meetup-meet-fans-all-over-the-world/": {
            "title": "iKON to hold its first online fan meetup\u2026 Meet fans all over the world",
            "content": ""
        },
        "https://kbopping.com/sistars-shake-it-perfectly-reinterpreted-in-queendom-2-loona-proves-performance-master/": {
            "title": "Sistar\u2019s \u2018Shake It\u2019 perfectly reinterpreted in \u2018Queendom 2\u2019, LOONA proves \u2018Performance Master\u2019",
            "content": ""
        },
        "https://kbopping.com/stray-kids-of-course-performance-mastermind/": {
            "title": "Stray Kids, of course! performance mastermind",
            "content": ""
        },
        "https://kbopping.com/k-pop-weekly-chart-youtube-2022-04-15/": {
            "title": "YouTube 100 in KoreaY",
            "content": ""
        },
        "https://kbopping.com/k-pop-daily-chart-apple-music-2022-04-16/": {
            "title": "APPLE MUSIC 100 in KoreaA",
            "content": ""
        },
        "https://kbopping.com/aespa-the-worlds-splendid-fashion/": {
            "title": "Aespa, the world\u2019s splendid fashion",
            "content": ""
        },
        "https://kbopping.com/blackpink-comeback-jennies-new-hairstyle-raises-fans-expectation/": {
            "title": "Blackpink comeback?  Jennie\u2019s new hairstyle raises fans\u2019 expectation",
            "content": ""
        },
        "https://kbopping.com/viviz-to-perform-for-grammys-global-spin-digital-series/": {
            "title": "Viviz to perform for Grammys\u2019 \u2018Global Spin!\u2019 digital series",
            "content": ""
        },
        "https://kbopping.com/seventeens-darling-global-popularity-expands-to-apple-stores-in-the-us/": {
            "title": "SEVENTEEN\u2019s \u2018Darl+ing\u2019 Global Popularity Expands to Apple Stores in the US",
            "content": ""
        },
        "https://kbopping.com/k-pop-weekly-chart-youtube-2022-04-08/": {
            "title": "YouTube 100 in KoreaY",
            "content": ""
        },
        "https://kbopping.com/k-pop-daily-chart-apple-music-2022-04-12/": {
            "title": "APPLE MUSIC 100 in KoreaA",
            "content": ""
        },
        "https://kbopping.com/expectations-for-tomorrow-x-togethers-comeback%e2%86%91-spoiler-week/": {
            "title": "Expectations for Tomorrow x Together\u2019s comeback\u2191..\u2019Spoiler Week\u2019",
            "content": ""
        },
        "https://kbopping.com/psy-releases-teaser-for-9th-album-everyday-that-shows-enthusiasm-for-drenched-show/": {
            "title": "PSY releases teaser for 9th album \u2018Everyday\u2019 that shows enthusiasm for \u2018Drenched Show\u2019",
            "content": ""
        },
        "https://kbopping.com/k-pop-daily-chart-apple-music-2022-04-14/": {
            "title": "APPLE MUSIC 100 in KoreaA",
            "content": ""
        },
        "https://kbopping.com/psy-showterview-scramble-ahead-of-comeback-prediction-of-special-chemistry-with-jessi/": {
            "title": "PSY, \u2018Showterview\u2019 scramble ahead of comeback\u2026 Prediction of special chemistry with Jessi",
            "content": ""
        },
        "https://kbopping.com/k-pop-weekly-chart-youtube-2022-04-01/": {
            "title": "YouTube 100 in KoreaY",
            "content": ""
        },
        "https://kbopping.com/just-b-comeback-with-just-begun/": {
            "title": "JUST B comeback with \u2018JUST BEGUN\u2019",
            "content": ""
        }
    }
}